sqltap/__init__.py
sqltap/sqltap.py
sqltap/wsgi.py
sqltap/templates/html.mako
sqltap/templates/text.mako
sqltap/templates/wsgi.mako
permit_sqltap-0.3.13.dist-info/LICENSE
permit_sqltap-0.3.13.dist-info/METADATA
permit_sqltap-0.3.13.dist-info/WHEEL
permit_sqltap-0.3.13.dist-info/top_level.txt
permit_sqltap-0.3.13.dist-info/RECORD
