Metadata-Version: 2.1
Name: permit-sqltap
Version: 0.3.13
Summary: Profiling and introspection for applications using sqlalchemy
Home-page: https://github.com/inconshreveable/sqltap
Author: inconshreveable
Author-email: alan@inconshreveable.com
Classifier: Development Status :: 4 - Beta
Classifier: Intended Audience :: Developers
Classifier: License :: OSI Approved :: Apache Software License
Classifier: Operating System :: OS Independent
Classifier: Programming Language :: Python :: 3
Classifier: Topic :: Database
License-File: LICENSE
Requires-Dist: SQLAlchemy (>=1.4)
Requires-Dist: Mako (>=0.4.1)
Requires-Dist: Werkzeug (>=0.9.6)
Requires-Dist: sqlparse (>=0.1.15)
Requires-Dist: gevent (>=22.10.2)
